autodpd/__init__.py
autodpd/autodpd.py
autodpd/static.py
autodpd/version.py
autodpd-0.2.1.dist-info/METADATA
autodpd-0.2.1.dist-info/WHEEL
autodpd-0.2.1.dist-info/entry_points.txt
autodpd-0.2.1.dist-info/RECORD
