Metadata-Version: 2.4
Name: autodpd
Version: 0.2.1
Summary: A Python package for automatically detecting project dependencies
Project-URL: Homepage, https://github.com/greatdanpeng/autodpd
Project-URL: Bug Tracker, https://github.com/greatdanpeng/autodpd/issues
Author-email: Dan Peng <dan.peng.1202@gmail.com>
Classifier: License :: OSI Approved :: MIT License
Classifier: Operating System :: OS Independent
Classifier: Programming Language :: Python :: 3
Requires-Python: >=3.6
Requires-Dist: packaging
Requires-Dist: requests
